intersight
