Metadata-Version: 2.4
Name: intersight
Version: 1.0.11.2025120106
Summary: The Python SDK for Cisco Intersight
Home-page: https://intersight.com
Author: Intersight API support
Author-email: intersight@cisco.com
License: Apache License 2.0
Keywords: Cisco Intersight
Classifier: License :: OSI Approved :: Apache Software License
Classifier: Natural Language :: English
Classifier: Operating System :: OS Independent
Requires-Python: >=3.6
License-File: LICENSE
Requires-Dist: urllib3>=1.25.3
Requires-Dist: python-dateutil
Requires-Dist: pem>=19.3.0
Requires-Dist: pycryptodome>=3.9.0
Dynamic: author
Dynamic: author-email
Dynamic: classifier
Dynamic: description
Dynamic: description-content-type
Dynamic: home-page
Dynamic: keywords
Dynamic: license
Dynamic: license-file
Dynamic: requires-dist
Dynamic: requires-python
Dynamic: summary
